{
  "水沸腾": [
    "水沸腾 filetype:PDF site:ustc.edu.cn",
    "中文",
    4
  ],
  "再次沸腾": [
    "再次沸腾 filetype:PDF site:ustc.edu.cn",
    "中文",
    3
  ],
  "沸点与气压的关系": [
    "沸点与气压的关系 filetype:PDF site:ustc.edu.cn",
    "中文",
    0
  ],
  "沸腾现象": [
    "沸腾现象 filetype:PDF site:ustc.edu.cn",
    "中文",
    3
  ],
  "热传递改变内能": [
    "热传递改变内能 filetype:PDF site:ustc.edu.cn",
    "中文",
    25
  ],
  "电压表": [
    "电压表 filetype:PDF site:ustc.edu.cn",
    "中文",
    28
  ],
  "电流表": [
    "电流表 filetype:PDF site:ustc.edu.cn",
    "中文",
    2
  ],
  "滑动变阻器": [
    "滑动变阻器 filetype:PDF site:ustc.edu.cn",
    "中文",
    0
  ],
  "定值电阻": [
    "定值电阻 filetype:PDF site:ustc.edu.cn",
    "中文",
    27
  ],
  "电源电压": [
    "电源电压 filetype:PDF site:ustc.edu.cn",
    "中文",
    18
  ],
  "欧姆定律": [
    "欧姆定律 filetype:PDF site:ustc.edu.cn",
    "中文",
    12
  ],
  "控制变量法实验设计": [
    "控制变量法实验设计 filetype:PDF site:ustc.edu.cn",
    "中文",
    28
  ],
  "滑动变阻器限流作用": [
    "滑动变阻器限流作用 filetype:PDF site:ustc.edu.cn",
    "中文",
    0
  ],
  "电热器": [
    "电热器 filetype:PDF site:ustc.edu.cn",
    "中文",
    7
  ],
  "简化电路": [
    "简化电路 filetype:PDF site:ustc.edu.cn",
    "中文",
    23
  ],
  "电热丝": [
    "电热丝 filetype:PDF site:ustc.edu.cn",
    "中文",
    1
  ],
  "高温挡": [
    "高温挡 filetype:PDF site:ustc.edu.cn",
    "中文",
    3
  ],
  "低温挡": [
    "低温挡 filetype:PDF site:ustc.edu.cn",
    "中文",
    3
  ],
  "功率": [
    "功率 filetype:PDF site:ustc.edu.cn",
    "中文",
    29
  ],
  "电压": [
    "电压 filetype:PDF site:ustc.edu.cn",
    "中文",
    30
  ],
  "阻值": [
    "阻值 filetype:PDF site:ustc.edu.cn",
    "中文",
    29
  ],
  "电功率计算公式": [
    "电功率计算公式 filetype:PDF site:ustc.edu.cn",
    "中文",
    1
  ],
  "串并联电路中电阻的等效关系": [
    "串并联电路中电阻的等效关系 filetype:PDF site:ustc.edu.cn",
    "中文",
    6
  ],
  "电热器挡位原理": [
    "电热器挡位原理 filetype:PDF site:ustc.edu.cn",
    "中文",
    1
  ],
  "压力作用效果": [
    "压力作用效果 filetype:PDF site:ustc.edu.cn",
    "中文",
    29
  ],
  "实验现象": [
    "实验现象 filetype:PDF site:ustc.edu.cn",
    "中文",
    29
  ],
  "图乙": [
    "图乙 filetype:PDF site:ustc.edu.cn",
    "中文",
    27
  ],
  "图丙": [
    "图丙 filetype:PDF site:ustc.edu.cn",
    "中文",
    27
  ],
  "压力作用效果的影响因素": [
    "压力作用效果的影响因素 filetype:PDF site:ustc.edu.cn",
    "中文",
    22
  ],
  "受力面积与压强的关系": [
    "受力面积与压强的关系 filetype:PDF site:ustc.edu.cn",
    "中文",
    8
  ],
  "控制变量法": [
    "控制变量法 filetype:PDF site:ustc.edu.cn",
    "中文",
    28
  ],
  "物体": [
    "物体 filetype:PDF site:ustc.edu.cn",
    "中文",
    30
  ],
  "做功": [
    "做功 filetype:PDF site:ustc.edu.cn",
    "中文",
    16
  ],
  "功的定义": [
    "功的定义 filetype:PDF site:ustc.edu.cn",
    "中文",
    1
  ],
  "力与位移的方向关系": [
    "力与位移的方向关系 filetype:PDF site:ustc.edu.cn",
    "中文",
    23
  ],
  "做功的两个必要因素": [
    "做功的两个必要因素 filetype:PDF site:ustc.edu.cn",
    "中文",
    1
  ],
  "时间": [
    "时间 filetype:PDF site:ustc.edu.cn",
    "中文",
    3
  ],
  "做功快": [
    "做功快 filetype:PDF site:ustc.edu.cn",
    "中文",
    3
  ],
  "功": [
    "功 filetype:PDF site:ustc.edu.cn",
    "中文",
    3
  ],
  "功率定义": [
    "功率定义 filetype:PDF site:ustc.edu.cn",
    "中文",
    4
  ]
}